tinyagents/__init__.py
tinyagents/callbacks.py
tinyagents/decorators.py
tinyagents/deployment_utils.py
tinyagents/graph.py
tinyagents/handlers.py
tinyagents/nodes/__init__.py
tinyagents/nodes/conditional_branch.py
tinyagents/nodes/node_meta.py
tinyagents/nodes/parallel.py
tinyagents/nodes/recursive.py
tinyagents/nodes/subgraph.py
tinyagents/tracing/__init__.py
tinyagents/tracing/decorators.py
tinyagents/tracing/utils.py
tinyagents/types.py
tinyagents/utils.py
tinyagents-1.2.0.dist-info/LICENSE
tinyagents-1.2.0.dist-info/METADATA
tinyagents-1.2.0.dist-info/WHEEL
tinyagents-1.2.0.dist-info/RECORD
