Metadata-Version: 2.1
Name: tinyagents
Version: 1.2.0
Summary: A tiny, lightweight and unintrusive library for orchestrating agentic applications.
Home-page: https://github.com/adam-h-ds/tinyagents
License: MIT
Author: Adam Hedib (adam-h-ds)
Requires-Python: >=3.10,<3.13
Classifier: License :: OSI Approved :: MIT License
Classifier: Programming Language :: Python :: 3
Classifier: Programming Language :: Python :: 3.10
Classifier: Programming Language :: Python :: 3.11
Classifier: Programming Language :: Python :: 3.12
Requires-Dist: arize-phoenix (>=4.24.0,<5.0.0)
Requires-Dist: opentelemetry-api (>=1.26.0,<2.0.0)
Requires-Dist: opentelemetry-exporter-otlp-proto-http (>=1.26.0,<2.0.0)
Requires-Dist: opentelemetry-sdk (>=1.26.0,<2.0.0)
Requires-Dist: ray[serve] (>=2.32.0,<3.0.0)
Project-URL: Repository, https://github.com/adam-h-ds/tinyagents
